churn-0.1.0.dist-info/DESCRIPTION.rst
churn-0.1.0.dist-info/METADATA
churn-0.1.0.dist-info/RECORD
churn-0.1.0.dist-info/WHEEL
churn-0.1.0.dist-info/entry_points.txt
churn-0.1.0.dist-info/metadata.json
churn-0.1.0.dist-info/top_level.txt
src/__init__.py
src/cli.py
src/errors.py
src/util.py
src/subcommands/__init__.py
src/subcommands/cards.py
src/subcommands/config.py
src/subcommands/initialize.py
src/subcommands/issuers.py
src/subcommands/networks.py
src/subcommands/payments.py
src/subcommands/programs.py
src/subcommands/reward_types.py
src/subcommands/rewards.py
src/subcommands/stats.py
src/subcommands/uninstall.py
